molpy/__init__.py
molpy/basis.py
molpy/errors.py
molpy/fchk.py
molpy/inporb.py
molpy/mh5.py
molpy/molden.py
molpy/orbitals.py
molpy/tools.py
molpy/wfn.py
molpy-1.0.data/scripts/penny
molpy-1.0.dist-info/DESCRIPTION.rst
molpy-1.0.dist-info/METADATA
molpy-1.0.dist-info/RECORD
molpy-1.0.dist-info/WHEEL
molpy-1.0.dist-info/metadata.json
molpy-1.0.dist-info/top_level.txt
