Metadata-Version: 2.0
Name: molpy
Version: 1.0
Summary: A package to handle Molcas wavefunction data
Home-page: https://github.com/steabert/molpy/
Author: Steven Vancoillie
Author-email: molpy@steven.se
License: GNU GPLv2
Platform: UNKNOWN
Requires: numpy
